[
  {
    "id": 1,
    "name": "Корм для собак Premium",
    "status": "В наличии",
    "photoUrl": "https://example.com/photos/dog_food_1.jpg",
    "description": "Высококачественный корм для собак, содержащий все необходимые питательные вещества.",
    "price": 499.99,
  },
  {
    "id": 2,
    "name": "Игрушка для кошек",
    "status": "В наличии",
    "photoUrl": "https://example.com/photos/cat_toy_1.jpg",
    "description": "Интерактивная игрушка для кошек, чтобы они оставались активными и развлекались.",
    "price": 299.99,
  }
]
